punpy/__init__.py
punpy/_version.py
punpy/main.py
punpy/digital_effects_table/__init__.py
punpy/digital_effects_table/digital_effects_table_templates.py
punpy/digital_effects_table/measurement_function.py
punpy/digital_effects_table/measurement_function_utils.py
punpy/digital_effects_table/tests/__init__.py
punpy/digital_effects_table/tests/make_digital_effects_table_gaslaw.py
punpy/digital_effects_table/tests/make_hypernets_det.py
punpy/digital_effects_table/tests/test_fillvalues.py
punpy/digital_effects_table/tests/test_measurement_function.py
punpy/digital_effects_table/tests/variables.py
punpy/lpu/__init__.py
punpy/lpu/lpu_propagation.py
punpy/lpu/tests/__init__.py
punpy/lpu/tests/test_lpu_propagation.py
punpy/mc/__init__.py
punpy/mc/mc_propagation.py
punpy/mc/tests/__init__.py
punpy/mc/tests/test_mc_propagation.py
punpy/utilities/__init__.py
punpy/utilities/correlation_forms.py
punpy/utilities/utilities.py
punpy/utilities/tests/__init__.py
punpy/utilities/tests/test_utilities.py
punpy-1.1.0.dist-info/licenses/LICENSE
punpy-1.1.0.dist-info/METADATA
punpy-1.1.0.dist-info/WHEEL
punpy-1.1.0.dist-info/top_level.txt
punpy-1.1.0.dist-info/RECORD
