Metadata-Version: 2.4
Name: punpy
Version: 1.1.0
Summary: Propagating UNcertainties in PYthon
Home-page: https://github.com/comet-toolkit/punpy
Author: CoMet Toolkit Team
Author-email: team@comet-toolkit.org
License: LGPLv3
License-File: LICENSE
Requires-Dist: comet_maths>=1.0.5
Requires-Dist: obsarray>=1.0.2
Provides-Extra: dev
Requires-Dist: pre-commit; extra == "dev"
Requires-Dist: tox; extra == "dev"
Requires-Dist: sphinx; extra == "dev"
Requires-Dist: sphinx_design; extra == "dev"
Requires-Dist: sphinx_book_theme; extra == "dev"
Requires-Dist: ipython; extra == "dev"
Requires-Dist: sphinx_autosummary_accessors; extra == "dev"
Dynamic: author
Dynamic: author-email
Dynamic: description
Dynamic: home-page
Dynamic: license
Dynamic: license-file
Dynamic: provides-extra
Dynamic: requires-dist
Dynamic: summary
